CHANGES.txt
LICENSE.txt
MANIFEST.in
README.rst
RELEASING.txt
TODO.txt
buildout.cfg
development.ini
production.ini
setup.cfg
setup.py
PyGall.egg-info/PKG-INFO
PyGall.egg-info/SOURCES.txt
PyGall.egg-info/dependency_links.txt
PyGall.egg-info/entry_points.txt
PyGall.egg-info/not-zip-safe
PyGall.egg-info/paster_plugins.txt
PyGall.egg-info/requires.txt
PyGall.egg-info/top_level.txt
pygall/__init__.py
pygall/forms.py
pygall/resources.py
pygall/security.py
pygall/subscribers.py
pygall/tests.py
pygall/views.py
pygall/lib/__init__.py
pygall/lib/archivefile.py
pygall/lib/helpers.py
pygall/lib/imageprocessing.py
pygall/lib/formalchemy/__init__.py
pygall/lib/formalchemy/pygallimage.py
pygall/locale/en/LC_MESSAGES/PyGall.mo
pygall/locale/fr/LC_MESSAGES/PyGall.mo
pygall/models/__init__.py
pygall/models/fspot.py
pygall/scripts/__init__.py
pygall/scripts/fspot_sync.py
pygall/scripts/setup.py
pygall/static/app/css/jquery.fileupload-ui.css
pygall/static/app/css/main.css
pygall/static/app/css/pbar-ani.gif
pygall/static/app/img/favicon.ico
pygall/static/app/js/App.Upload.js
pygall/static/app/js/jquery.fileupload-ui.js
pygall/static/app/js/jquery.fileupload.js
pygall/static/app/js/jquery.iframe-transport.js
pygall/static/app/js/jquery_fix_csrf.js
pygall/static/build/galleria.min.js
pygall/static/build/jquery.fileupload-ui.min.css
pygall/static/build/main.min.css
pygall/static/build/upload.min.js
pygall/static/lib/galleria/docs/jsdoc/src/app/frame.js
pygall/static/lib/galleria/docs/jsdoc/src/app/main.js
pygall/static/lib/galleria/docs/jsdoc/src/app/run.js
pygall/static/lib/galleria/docs/jsdoc/src/app/test.js
pygall/static/lib/galleria/docs/jsdoc/src/app/frame/Chain.js
pygall/static/lib/galleria/docs/jsdoc/src/app/frame/Dumper.js
pygall/static/lib/galleria/docs/jsdoc/src/app/frame/Hash.js
pygall/static/lib/galleria/docs/jsdoc/src/app/frame/Link.js
pygall/static/lib/galleria/docs/jsdoc/src/app/frame/Namespace.js
pygall/static/lib/galleria/docs/jsdoc/src/app/frame/Opt.js
pygall/static/lib/galleria/docs/jsdoc/src/app/frame/Reflection.js
pygall/static/lib/galleria/docs/jsdoc/src/app/frame/String.js
pygall/static/lib/galleria/docs/jsdoc/src/app/frame/Testrun.js
pygall/static/lib/galleria/docs/jsdoc/src/app/handlers/FOODOC.js
