Metadata-Version: 1.0
Name: PyGall
Version: 0.11
Summary: Image gallery built with Pyramid web framework
Home-page: http://gitorious.org/PyGall
Author: Bruno Binet
Author-email: binet.bruno@gmail.com
License: BSD
Keywords: web wsgi pylons pyramid image photo web gallery
Platform: UNKNOWN
Classifier: Development Status :: 3 - Alpha
Classifier: Environment :: Web Environment
Classifier: Intended Audience :: End Users/Desktop
Classifier: License :: OSI Approved :: BSD License
Classifier: Operating System :: OS Independent
Classifier: Programming Language :: Python
Classifier: Programming Language :: JavaScript
Classifier: Framework :: Pylons
Classifier: Topic :: Internet :: WWW/HTTP
Classifier: Topic :: Internet :: WWW/HTTP :: WSGI
Classifier: Topic :: Internet :: WWW/HTTP :: WSGI :: Application
